oslo_privsep/__init__.py
oslo_privsep/_i18n.py
oslo_privsep/capabilities.py
oslo_privsep/comm.py
oslo_privsep/daemon.py
oslo_privsep/priv_context.py
oslo_privsep/version.py
oslo_privsep/functional/__init__.py
oslo_privsep/functional/test_daemon.py
oslo_privsep/locale/de/LC_MESSAGES/oslo_privsep.po
oslo_privsep/locale/en_GB/LC_MESSAGES/oslo_privsep.po
oslo_privsep/tests/__init__.py
oslo_privsep/tests/fixture.py
oslo_privsep/tests/test_capabilities.py
oslo_privsep/tests/test_comm.py
oslo_privsep/tests/test_daemon.py
oslo_privsep/tests/test_priv_context.py
oslo_privsep/tests/testctx.py
oslo_privsep-3.7.0.dist-info/AUTHORS
oslo_privsep-3.7.0.dist-info/LICENSE
oslo_privsep-3.7.0.dist-info/METADATA
oslo_privsep-3.7.0.dist-info/WHEEL
oslo_privsep-3.7.0.dist-info/entry_points.txt
oslo_privsep-3.7.0.dist-info/pbr.json
oslo_privsep-3.7.0.dist-info/top_level.txt
oslo_privsep-3.7.0.dist-info/RECORD
