Metadata-Version: 2.1
Name: oslo.privsep
Version: 3.7.0
Summary: OpenStack library for privilege separation
Home-page: https://docs.openstack.org/oslo.privsep/latest/
Author: OpenStack
Author-email: openstack-discuss@lists.openstack.org
Classifier: Environment :: OpenStack
Classifier: Intended Audience :: Information Technology
Classifier: Intended Audience :: System Administrators
Classifier: License :: OSI Approved :: Apache Software License
Classifier: Operating System :: POSIX :: Linux
Classifier: Programming Language :: Python
Classifier: Programming Language :: Python :: 3
Classifier: Programming Language :: Python :: 3.9
Classifier: Programming Language :: Python :: 3.10
Classifier: Programming Language :: Python :: 3.11
Classifier: Programming Language :: Python :: 3.12
Classifier: Programming Language :: Python :: 3 :: Only
Classifier: Programming Language :: Python :: Implementation :: CPython
Requires-Python: >=3.9
License-File: LICENSE
License-File: AUTHORS
Requires-Dist: oslo.log >=5.0.2
Requires-Dist: oslo.i18n >=3.15.3
Requires-Dist: oslo.config >=5.2.0
Requires-Dist: oslo.utils >=3.33.0
Requires-Dist: cffi >=1.14.0
Requires-Dist: eventlet >=0.21.0
Requires-Dist: greenlet >=0.4.14
Requires-Dist: msgpack >=0.6.0
Requires-Dist: debtcollector >=3.0.0
